{"Capital":"Baku","Continent":"AS","Country_Name":"Azerbaijan","DS":"AZ","Dial":"994","EDGAR":"1D","FIFA":"AZE","FIPS":"AJ","GAUL":"19","Geo_Name_ID":"587116","IOC":"AZE","ISO3166_1_Alpha_2":"AZ","ISO3166_1_Alpha_3":"AZE","ISO4217_Currency_Alphabetic_Code":"AZN","ISO4217_Currency_Country_Name":"AZERBAIJAN","ISO4217_Currency_Minor_Unit":2,"ISO4217_Currency_Name":"Azerbaijanian Manat","ISO4217_Currency_Numeric_Code":944,"ITU":"AZE","Is_Independent":"Yes","Languages":"az,ru,hy","M49":31,"MARC":"aj","Official_Name_English":"Azerbaijan","TLD":".az","WMO":"AJ"}