{"Capital":"West Island","Continent":"AS","Country_Name":"Cocos (Keeling) Islands","DS":"AUS","Dial":"61","EDGAR":null,"FIFA":"CCK","FIPS":"CK","GAUL":"56","Geo_Name_ID":"1547376","IOC":null,"ISO3166_1_Alpha_2":"CC","ISO3166_1_Alpha_3":"CCK","ISO4217_Currency_Alphabetic_Code":null,"ISO4217_Currency_Country_Name":null,"ISO4217_Currency_Minor_Unit":null,"ISO4217_Currency_Name":null,"ISO4217_Currency_Numeric_Code":null,"ITU":"ICO","Is_Independent":"Territory of AU","Languages":"ms-CC,en","M49":166,"MARC":"xb","Official_Name_English":null,"TLD":".cc","WMO":"KK"}