{"Capital":"San Jose","Continent":"NA","Country_Name":"Costa Rica","DS":"CR","Dial":"506","EDGAR":"G2","FIFA":"CRC","FIPS":"CS","GAUL":"61","Geo_Name_ID":"3624060","IOC":"CRC","ISO3166_1_Alpha_2":"CR","ISO3166_1_Alpha_3":"CRI","ISO4217_Currency_Alphabetic_Code":"CRC","ISO4217_Currency_Country_Name":"COSTA RICA","ISO4217_Currency_Minor_Unit":2,"ISO4217_Currency_Name":"Costa Rican Colon","ISO4217_Currency_Numeric_Code":188,"ITU":"CTR","Is_Independent":"Yes","Languages":"es-CR,en","M49":188,"MARC":"cr","Official_Name_English":"Costa Rica","TLD":".cr","WMO":"CS"}