{"Capital":"Dublin","Continent":"EU","Country_Name":"Ireland","DS":"IRL","Dial":"353","EDGAR":"L2","FIFA":"IRL","FIPS":"EI","GAUL":"119","Geo_Name_ID":"2963597","IOC":"IRL","ISO3166_1_Alpha_2":"IE","ISO3166_1_Alpha_3":"IRL","ISO4217_Currency_Alphabetic_Code":"EUR","ISO4217_Currency_Country_Name":"IRELAND","ISO4217_Currency_Minor_Unit":2,"ISO4217_Currency_Name":"Euro","ISO4217_Currency_Numeric_Code":978,"ITU":"IRL","Is_Independent":"Yes","Languages":"en-IE,ga-IE","M49":372,"MARC":"ie","Official_Name_English":"Ireland","TLD":".ie","WMO":"IE"}