{"Capital":"Longyearbyen","Continent":"EU","Country_Name":"Svalbard & Jan Mayen","DS":null,"Dial":"47","EDGAR":"L9","FIFA":null,"FIPS":"SV,JN","GAUL":"234","Geo_Name_ID":"607072","IOC":null,"ISO3166_1_Alpha_2":"SJ","ISO3166_1_Alpha_3":"SJM","ISO4217_Currency_Alphabetic_Code":"NOK","ISO4217_Currency_Country_Name":"SVALBARD AND JAN MAYEN","ISO4217_Currency_Minor_Unit":2,"ISO4217_Currency_Name":"Norwegian Krone","ISO4217_Currency_Numeric_Code":578,"ITU":"NOR","Is_Independent":"Territory of NO","Languages":"no,ru","M49":744,"MARC":null,"Official_Name_English":"Svalbard and Jan Mayen Islands","TLD":".sj","WMO":"SZ"}